rl/__init__.py
rl/agent.py
rl/callbacks.py
rl/keras_future.py
rl/memory.py
rl/metrics.py
rl/policy.py
rl/random.py
rl/agents/__init__.py
rl/agents/cem.py
rl/agents/ddpg.py
rl/agents/dqn.py
rl/agents/sarsa.py
rl/hooks/__init__.py
rl/hooks/hook.py
rl/hooks/plot.py
rl/hooks/tensorboard.py
rl/utils/__init__.py
rl/utils/env.py
rl/utils/networks.py
rl/utils/numerics.py
rl/utils/plot.py
rl/utils/stats.py
rl/utils/util.py
vinci-1.0.0.dist-info/DESCRIPTION.rst
vinci-1.0.0.dist-info/METADATA
vinci-1.0.0.dist-info/RECORD
vinci-1.0.0.dist-info/WHEEL
vinci-1.0.0.dist-info/metadata.json
vinci-1.0.0.dist-info/top_level.txt
