Metadata-Version: 2.0
Name: vinci
Version: 1.0.0
Summary: Deep Reinforcement Learning framework
Home-page: https://github.com/phylliade/vinci
Author: Pierre Manceron
Author-email: UNKNOWN
License: MIT
Platform: UNKNOWN
Requires-Dist: gym (>=0.9.2)
Requires-Dist: keras (>=2.0.0)
Requires-Dist: numpy
Provides-Extra: plot
Requires-Dist: matplotlib; extra == 'plot'
Requires-Dist: seaborn; extra == 'plot'
